<annotation>
	<folder>9f247-nNmrnArTomAba-output</folder>
	<filename>circuit921.jpg</filename>
	<path>/Users/Joe/Documents/Data-Unlabelled/9f247-nNmrnArTomAba-output/circuit921.jpg</path>
	<source>
		<database>Unknown</database>
	</source>
	<size>
		<width>2950</width>
		<height>2956</height>
		<depth>3</depth>
	</size>
	<segmented>0</segmented>
	<object>
		<name>LED</name>
		<pose>Unspecified</pose>
		<truncated>0</truncated>
		<difficult>0</difficult>
		<bndbox>
			<xmin>2497</xmin>
			<ymin>576</ymin>
			<xmax>2700</xmax>
			<ymax>761</ymax>
		</bndbox>
	</object>
	<object>
		<name>LED</name>
		<pose>Unspecified</pose>
		<truncated>0</truncated>
		<difficult>0</difficult>
		<bndbox>
			<xmin>2491</xmin>
			<ymin>773</ymin>
			<xmax>2711</xmax>
			<ymax>949</ymax>
		</bndbox>
	</object>
	<object>
		<name>LED</name>
		<pose>Unspecified</pose>
		<truncated>0</truncated>
		<difficult>0</difficult>
		<bndbox>
			<xmin>2494</xmin>
			<ymin>958</ymin>
			<xmax>2726</xmax>
			<ymax>1141</ymax>
		</bndbox>
	</object>
	<object>
		<name>LED</name>
		<pose>Unspecified</pose>
		<truncated>0</truncated>
		<difficult>0</difficult>
		<bndbox>
			<xmin>2497</xmin>
			<ymin>1149</ymin>
			<xmax>2726</xmax>
			<ymax>1323</ymax>
		</bndbox>
	</object>
	<object>
		<name>LED</name>
		<pose>Unspecified</pose>
		<truncated>0</truncated>
		<difficult>0</difficult>
		<bndbox>
			<xmin>2500</xmin>
			<ymin>1329</ymin>
			<xmax>2729</xmax>
			<ymax>1497</ymax>
		</bndbox>
	</object>
	<object>
		<name>LED</name>
		<pose>Unspecified</pose>
		<truncated>0</truncated>
		<difficult>0</difficult>
		<bndbox>
			<xmin>2500</xmin>
			<ymin>1523</ymin>
			<xmax>2717</xmax>
			<ymax>1708</ymax>
		</bndbox>
	</object>
	<object>
		<name>LED</name>
		<pose>Unspecified</pose>
		<truncated>0</truncated>
		<difficult>0</difficult>
		<bndbox>
			<xmin>2479</xmin>
			<ymin>1694</ymin>
			<xmax>2691</xmax>
			<ymax>1864</ymax>
		</bndbox>
	</object>
	<object>
		<name>LED</name>
		<pose>Unspecified</pose>
		<truncated>0</truncated>
		<difficult>0</difficult>
		<bndbox>
			<xmin>2476</xmin>
			<ymin>1873</ymin>
			<xmax>2706</xmax>
			<ymax>2052</ymax>
		</bndbox>
	</object>
	<object>
		<name>LED</name>
		<pose>Unspecified</pose>
		<truncated>0</truncated>
		<difficult>0</difficult>
		<bndbox>
			<xmin>2476</xmin>
			<ymin>2044</ymin>
			<xmax>2720</xmax>
			<ymax>2244</ymax>
		</bndbox>
	</object>
	<object>
		<name>LED</name>
		<pose>Unspecified</pose>
		<truncated>0</truncated>
		<difficult>0</difficult>
		<bndbox>
			<xmin>2479</xmin>
			<ymin>2223</ymin>
			<xmax>2688</xmax>
			<ymax>2429</ymax>
		</bndbox>
	</object>
	<object>
		<name>Capacitor</name>
		<pose>Unspecified</pose>
		<truncated>0</truncated>
		<difficult>0</difficult>
		<bndbox>
			<xmin>1264</xmin>
			<ymin>1391</ymin>
			<xmax>1420</xmax>
			<ymax>1635</ymax>
		</bndbox>
	</object>
	<object>
		<name>Capacitor</name>
		<pose>Unspecified</pose>
		<truncated>0</truncated>
		<difficult>0</difficult>
		<bndbox>
			<xmin>1503</xmin>
			<ymin>1182</ymin>
			<xmax>1688</xmax>
			<ymax>1405</ymax>
		</bndbox>
	</object>
	<object>
		<name>Capacitor</name>
		<pose>Unspecified</pose>
		<truncated>0</truncated>
		<difficult>0</difficult>
		<bndbox>
			<xmin>1635</xmin>
			<ymin>849</ymin>
			<xmax>1797</xmax>
			<ymax>1014</ymax>
		</bndbox>
	</object>
	<object>
		<name>Capacitor</name>
		<pose>Unspecified</pose>
		<truncated>0</truncated>
		<difficult>0</difficult>
		<bndbox>
			<xmin>1864</xmin>
			<ymin>767</ymin>
			<xmax>2026</xmax>
			<ymax>1005</ymax>
		</bndbox>
	</object>
</annotation>
